{"inkVersion":20,"root":[["^blank?","\n","^Hello! Hi! Salutations!","\n","^I see that you're up now, that's fantastic!","\n",["ev",{"^->":"0.6.$r1"},{"temp=":"$r"},"str",{"->":".^.s"},[{"#n":"$r1"}],"/str","/ev",{"*":"0.c-0","flg":2},{"s":["^Where am I? ",{"->":"$r","var":true},null]}],["ev",{"^->":"0.7.$r1"},{"temp=":"$r"},"str",{"->":".^.s"},[{"#n":"$r1"}],"/str","/ev",{"*":"0.c-1","flg":2},{"s":["^Who are you? ",{"->":"$r","var":true},null]}],{"c-0":["ev",{"^->":"0.c-0.$r2"},"/ev",{"temp=":"$r"},{"->":"0.6.s"},[{"#n":"$r2"}],{"->":"Laugh"},"\n",{"->":"0.g-0"},{"#f":5}],"c-1":["ev",{"^->":"0.c-1.$r2"},"/ev",{"temp=":"$r"},{"->":"0.7.s"},[{"#n":"$r2"}],{"->":"Laugh"},"\n",{"->":"0.g-0"},{"#f":5}],"g-0":["done",{"#f":5}]}],"done",{"Laugh":["^Oh hoho no need to worry about such trivial things! You've already started walking, so why don't we skip the readjustment period?","\n","^Let us see how those new fleshy bits work.","\n","^Try picking up that box behind me by pressing \"Z\"","\n","end",{"#f":1}],"#f":1}],"listDefs":{}}